huaweicloudsdker/__init__.py
huaweicloudsdker/v3/__init__.py
huaweicloudsdker/v3/er_async_client.py
huaweicloudsdker/v3/er_client.py
huaweicloudsdker/v3/model/__init__.py
huaweicloudsdker/v3/model/accept_attachment_request.py
huaweicloudsdker/v3/model/accept_attachment_response.py
huaweicloudsdker/v3/model/associate_route_table_request.py
huaweicloudsdker/v3/model/associate_route_table_response.py
huaweicloudsdker/v3/model/association.py
huaweicloudsdker/v3/model/association_request_body.py
huaweicloudsdker/v3/model/association_route_policy_request_body.py
huaweicloudsdker/v3/model/attachment_details.py
huaweicloudsdker/v3/model/attachment_response.py
huaweicloudsdker/v3/model/available_zone.py
huaweicloudsdker/v3/model/batch_create_resource_tags_request.py
huaweicloudsdker/v3/model/batch_create_resource_tags_response.py
huaweicloudsdker/v3/model/batch_operate_resource_tags_request_body.py
huaweicloudsdker/v3/model/change_association_route_policy_request.py
huaweicloudsdker/v3/model/change_association_route_policy_response.py
huaweicloudsdker/v3/model/change_availability_zone_request.py
huaweicloudsdker/v3/model/change_availability_zone_response.py
huaweicloudsdker/v3/model/create_enterprise_router.py
huaweicloudsdker/v3/model/create_enterprise_router_request.py
huaweicloudsdker/v3/model/create_enterprise_router_request_body.py
huaweicloudsdker/v3/model/create_enterprise_router_response.py
huaweicloudsdker/v3/model/create_flow_log_request.py
huaweicloudsdker/v3/model/create_flow_log_request_body.py
huaweicloudsdker/v3/model/create_flow_log_response.py
huaweicloudsdker/v3/model/create_resource_tag_request.py
huaweicloudsdker/v3/model/create_resource_tag_request_body.py
huaweicloudsdker/v3/model/create_resource_tag_response.py
huaweicloudsdker/v3/model/create_route.py
huaweicloudsdker/v3/model/create_route_request_body.py
huaweicloudsdker/v3/model/create_route_table.py
huaweicloudsdker/v3/model/create_route_table_request.py
huaweicloudsdker-3.1.184.dist-info/METADATA
huaweicloudsdker-3.1.184.dist-info/WHEEL
huaweicloudsdker-3.1.184.dist-info/licenses/LICENSE
huaweicloudsdker-3.1.184.dist-info/RECORD
